[
  {
    "id": "w4-b1",
    "week": 4,
    "title": "配列の要素を表示",
    "level": "basic",
    "section": "配列編",
    "type": "execution",
    "question": "配列 `fruits` に [\"りんご\", \"バナナ\", \"みかん\"] を代入し、最初の要素を `console.log` で表示してください。",
    "starterCode": "// ここにコードを書いてください\n",
    "answer": "const fruits = [\"りんご\", \"バナナ\", \"みかん\"];\nconsole.log(fruits[0]);",
    "explanation": "配列は `[]` で作成し、インデックス（0から始まる番号）で要素にアクセスします。HTMLのリスト項目を配列で管理するイメージです。",
    "learningPoints": [
      "配列は [] で作成する",
      "インデックスは 0 から始まる",
      "array[0] で最初の要素にアクセスできる"
    ],
    "hints": [
      "const fruits = [\"りんご\", \"バナナ\", \"みかん\"]; で配列を作ります",
      "fruits[0] で最初の要素を取得できます"
    ],
    "testCases": [
      { "input": [], "expected": "りんご" }
    ]
  },
  {
    "id": "w4-b2",
    "week": 4,
    "title": "2番目の要素を取得",
    "level": "basic",
    "section": "配列編",
    "type": "execution",
    "question": "配列 `colors` に [\"red\", \"green\", \"blue\"] を代入し、2番目の要素を `console.log` で表示してください。",
    "starterCode": "// ここにコードを書いてください\n",
    "answer": "const colors = [\"red\", \"green\", \"blue\"];\nconsole.log(colors[1]);",
    "explanation": "配列のインデックスは 0 から数えます。1番目は `[0]`、2番目は `[1]`、3番目は `[2]` です。",
    "learningPoints": [
      "2番目の要素はインデックス 1",
      "人間の数え方（1から）とインデックス（0から）は1つずれる",
      "array[1] で2番目の要素にアクセスできる"
    ],
    "hints": [
      "2番目の要素は colors[1] です",
      "console.log(colors[1]); で表示できます"
    ],
    "testCases": [
      { "input": [], "expected": "green" }
    ]
  },
  {
    "id": "w4-b3",
    "week": 4,
    "title": "配列の長さ",
    "level": "basic",
    "section": "配列編",
    "type": "execution",
    "question": "配列 `colors` に [\"red\", \"green\", \"blue\", \"yellow\"] を代入し、配列の要素数を `console.log` で表示してください。",
    "starterCode": "// ここにコードを書いてください\n",
    "answer": "const colors = [\"red\", \"green\", \"blue\", \"yellow\"];\nconsole.log(colors.length);",
    "explanation": "配列の `.length` プロパティで要素数を取得できます。リストの項目数を数える操作と同じです。",
    "learningPoints": [
      ".length で配列の要素数を取得できる",
      "length はプロパティ（関数ではない）",
      "空配列の length は 0"
    ],
    "hints": [
      "colors.length で要素数がわかります",
      "console.log(colors.length); で表示しましょう"
    ],
    "testCases": [
      { "input": [], "expected": "4" }
    ]
  },
  {
    "id": "w4-b4",
    "week": 4,
    "title": "for文で繰り返し",
    "level": "basic",
    "section": "配列編",
    "type": "execution",
    "question": "for文を使って 1 から 3 までを順番に `console.log` で表示してください。",
    "starterCode": "// ここにコードを書いてください\n",
    "answer": "for (let i = 1; i <= 3; i++) {\n  console.log(i);\n}",
    "explanation": "`for (初期化; 条件; 更新)` の3つの部分で繰り返しを制御します。次の問題では、この for文を使って配列の要素を順番に処理します。",
    "learningPoints": [
      "for文の3つの部分：初期化・条件・更新",
      "let は再代入可能な変数を宣言する",
      "i++ は i を1増やす（インクリメント）"
    ],
    "hints": [
      "for (let i = 1; i <= 3; i++) { ... } の形式です",
      "ループ内で console.log(i); を呼びます"
    ],
    "testCases": [
      { "input": [], "expected": "1\n2\n3" }
    ]
  },
  {
    "id": "w4-b5",
    "week": 4,
    "title": "for文で配列を表示",
    "level": "basic",
    "section": "配列編",
    "type": "execution",
    "question": "配列 `items` に [\"A\", \"B\", \"C\"] を代入し、for文と `items.length` を使って全要素を1行ずつ `console.log` で表示してください。",
    "starterCode": "const items = [\"A\", \"B\", \"C\"];\n// ここにfor文を書いてください\n",
    "answer": "const items = [\"A\", \"B\", \"C\"];\nfor (let i = 0; i < items.length; i++) {\n  console.log(items[i]);\n}",
    "explanation": "`for (let i = 0; i < array.length; i++)` は配列の全要素を順番に処理する基本パターンです。リスト表示の土台になる書き方です。",
    "learningPoints": [
      "i = 0 から length 未満までループする",
      "items[i] で i 番目の要素にアクセスできる",
      "配列の要素数に合わせて繰り返せる"
    ],
    "hints": [
      "for (let i = 0; i < items.length; i++) { ... } の形式です",
      "ループ内で console.log(items[i]); を呼びます"
    ],
    "testCases": [
      { "input": [], "expected": "A\nB\nC" }
    ]
  },
  {
    "id": "w4-b6",
    "week": 4,
    "title": "最後の要素を取得",
    "level": "basic",
    "section": "配列編",
    "type": "execution",
    "question": "配列 `fruits` に [\"りんご\", \"バナナ\", \"みかん\"] を代入し、最後の要素を `console.log` で表示してください。",
    "starterCode": "const fruits = [\"りんご\", \"バナナ\", \"みかん\"];\n// ここにコードを書いてください\n",
    "answer": "const fruits = [\"りんご\", \"バナナ\", \"みかん\"];\nconsole.log(fruits[fruits.length - 1]);",
    "explanation": "最後の要素のインデックスは `length - 1` です。配列の長さが変わっても、常に最後の要素を取得できます。",
    "learningPoints": [
      "最後のインデックスは length - 1",
      "fruits[fruits.length - 1] で最後の要素を取得できる",
      "インデックスと length の関係を理解する"
    ],
    "hints": [
      "最後の要素は fruits[fruits.length - 1] です",
      "console.log(fruits[fruits.length - 1]); で表示できます"
    ],
    "testCases": [
      { "input": [], "expected": "みかん" }
    ]
  },
  {
    "id": "w4-b7",
    "week": 4,
    "title": "pushで要素を追加",
    "level": "basic",
    "section": "メソッド編",
    "type": "execution",
    "question": "配列 `tags` に [\"HTML\", \"CSS\"] を代入し、`push` で \"JavaScript\" を追加したあと、追加した要素（3番目）を `console.log` で表示してください。",
    "starterCode": "const tags = [\"HTML\", \"CSS\"];\n// ここにコードを書いてください\n",
    "answer": "const tags = [\"HTML\", \"CSS\"];\ntags.push(\"JavaScript\");\nconsole.log(tags[2]);",
    "explanation": "`.push()` は配列の末尾に要素を追加するメソッドです。戻り値は新しい length であり、配列そのものではない点に注意してください。",
    "learningPoints": [
      "push() で配列の末尾に要素を追加できる",
      "push() の戻り値は配列ではなく length",
      "const でも配列の中身は変更できる"
    ],
    "hints": [
      "tags.push(\"JavaScript\"); で要素を追加します",
      "追加後の3番目は tags[2] です"
    ],
    "testCases": [
      { "input": [], "expected": "JavaScript" }
    ]
  },
  {
    "id": "w4-b8",
    "week": 4,
    "title": "forEachで順番に処理",
    "level": "basic",
    "section": "メソッド編",
    "type": "execution",
    "question": "配列 `items` に [\"A\", \"B\", \"C\"] を代入し、`forEach` で各要素を1行ずつ `console.log` で表示してください。",
    "starterCode": "const items = [\"A\", \"B\", \"C\"];\n// ここにforEachを書いてください\n",
    "answer": "const items = [\"A\", \"B\", \"C\"];\nitems.forEach(function (item) {\n  console.log(item);\n});",
    "explanation": "`.forEach()` は配列の各要素に対して処理を実行するメソッドです。for文の代わりに使え、リストの各項目を処理するときによく使います。",
    "learningPoints": [
      "forEach で配列の全要素を順番に処理できる",
      "コールバック関数の引数 item が各要素になる",
      "for文と同じ結果をより簡潔に書ける"
    ],
    "hints": [
      "items.forEach(function (...) { ... }); の形式です。コールバックの第1引数が各要素になります",
      "コールバック内で各要素を console.log します"
    ],
    "testCases": [
      { "input": [], "expected": "A\nB\nC" }
    ]
  },
  {
    "id": "w4-b9",
    "week": 4,
    "title": "includesで含まれるか確認",
    "level": "basic",
    "section": "メソッド編",
    "type": "execution",
    "question": "配列 `skills` に [\"HTML\", \"CSS\", \"JavaScript\"] を代入し、`includes` を使って \"CSS\" が含まれるかどうかを `console.log` で表示してください。",
    "starterCode": "const skills = [\"HTML\", \"CSS\", \"JavaScript\"];\n// ここにコードを書いてください\n",
    "answer": "const skills = [\"HTML\", \"CSS\", \"JavaScript\"];\nconsole.log(skills.includes(\"CSS\"));",
    "explanation": "`.includes()` は配列に指定した値が含まれるかを `true` / `false` で返します。選択状態の確認や、表示・非表示の切り替え判定によく使います。",
    "learningPoints": [
      "includes() は true / false を返す",
      "配列に特定の値があるか調べられる",
      "条件分岐と組み合わせやすい"
    ],
    "hints": [
      "skills.includes(\"CSS\") で確認できます",
      "console.log(skills.includes(\"CSS\")); で表示しましょう"
    ],
    "testCases": [
      { "input": [], "expected": "true" }
    ]
  },
  {
    "id": "w4-b10",
    "week": 4,
    "title": "joinで文字列に結合",
    "level": "basic",
    "section": "メソッド編",
    "type": "execution",
    "question": "配列 `tags` に [\"HTML\", \"CSS\", \"JavaScript\"] を代入し、`join(\", \")` でカンマ区切りの1つの文字列にして `console.log` で表示してください。",
    "starterCode": "const tags = [\"HTML\", \"CSS\", \"JavaScript\"];\n// ここにコードを書いてください\n",
    "answer": "const tags = [\"HTML\", \"CSS\", \"JavaScript\"];\nconsole.log(tags.join(\", \"));",
    "explanation": "`.join()` は配列の要素を指定した区切り文字でつないで、1つの文字列にします。タグ一覧やパンくずリストの表示に使える考え方です。",
    "learningPoints": [
      "join() で配列を1つの文字列にできる",
      "区切り文字を引数で指定する",
      "リスト表示の基礎になる"
    ],
    "hints": [
      "tags.join(\", \") でカンマ+スペース区切りになります",
      "console.log(tags.join(\", \")); で表示しましょう"
    ],
    "testCases": [
      { "input": [], "expected": "HTML, CSS, JavaScript" }
    ]
  },
  {
    "id": "w4-b11",
    "week": 4,
    "title": "sliceで一部を取り出す",
    "level": "basic",
    "section": "メソッド編",
    "type": "execution",
    "question": "配列 `colors` に [\"red\", \"green\", \"blue\", \"yellow\"] を代入し、`slice(0, 2)` で先頭2つの要素を取り出した配列の要素数を `console.log` で表示してください。",
    "starterCode": "const colors = [\"red\", \"green\", \"blue\", \"yellow\"];\n// ここにコードを書いてください\n",
    "answer": "const colors = [\"red\", \"green\", \"blue\", \"yellow\"];\nconst firstTwo = colors.slice(0, 2);\nconsole.log(firstTwo.length);",
    "explanation": "`.slice()` は配列の一部をコピーして新しい配列を返します。元の配列は変わりません。状態を壊さずにデータを扱う考え方の基礎になります。",
    "learningPoints": [
      "slice(開始, 終了) で一部を取り出せる",
      "元の配列は変更されない",
      "新しい配列が返る"
    ],
    "hints": [
      "colors.slice(0, 2) で先頭2つの要素を取り出せます",
      "取り出した配列の .length で要素数を確認できます"
    ],
    "testCases": [
      { "input": [], "expected": "2" }
    ]
  },
  {
    "id": "w4-b12",
    "week": 4,
    "title": "indexOfで位置を調べる",
    "level": "basic",
    "section": "メソッド編",
    "type": "execution",
    "question": "配列 `fruits` に [\"りんご\", \"バナナ\", \"みかん\"] を代入し、`indexOf` を使って \"バナナ\" のインデックスを `console.log` で表示してください。",
    "starterCode": "const fruits = [\"りんご\", \"バナナ\", \"みかん\"];\n// ここにコードを書いてください\n",
    "answer": "const fruits = [\"りんご\", \"バナナ\", \"みかん\"];\nconsole.log(fruits.indexOf(\"バナナ\"));",
    "explanation": "`.indexOf()` は指定した値が配列の何番目にあるか（インデックス）を返します。見つからない場合は `-1` を返します。",
    "learningPoints": [
      "indexOf() で要素の位置（インデックス）がわかる",
      "見つからないときは -1",
      "配列内の特定項目を探すときに使う"
    ],
    "hints": [
      "fruits.indexOf(\"バナナ\") で位置を調べられます",
      "console.log(fruits.indexOf(\"バナナ\")); で表示しましょう"
    ],
    "testCases": [
      { "input": [], "expected": "1" }
    ]
  },
  {
    "id": "w4-a1",
    "week": 4,
    "title": "配列の合計を求める",
    "level": "advanced",
    "section": "配列編",
    "type": "execution",
    "question": "数値の配列 `scores` に [80, 90, 70] を代入し、for文と `scores.length` を使って全要素の合計を `console.log` で表示してください。",
    "starterCode": "const scores = [80, 90, 70];\n// ここにfor文を書いてください\n",
    "answer": "const scores = [80, 90, 70];\nlet total = 0;\nfor (let i = 0; i < scores.length; i++) {\n  total += scores[i];\n}\nconsole.log(total);",
    "explanation": "for文で配列を1つずつ処理し、合計用の変数に足し込むパターンです。点数の合計や売上の集計など、実務でもよく使う処理です。",
    "learningPoints": [
      "for文で配列の全要素を順番に処理できる",
      "let で合計用の変数を用意し += で足し込める",
      "length を使えば要素数が変わっても同じコードで動く"
    ],
    "hints": [
      "let total = 0; で合計用の変数を用意します",
      "for (let i = 0; i < scores.length; i++) { total += scores[i]; } のように足し込みます",
      "ループのあと console.log(total); で合計を表示します"
    ],
    "testCases": [
      { "input": [], "expected": "240" }
    ]
  },
  {
    "id": "w4-a2",
    "week": 4,
    "title": "スキルを追加して表示",
    "level": "advanced",
    "section": "メソッド編",
    "type": "execution",
    "question": "配列 `skills` に [\"HTML\", \"CSS\"] を代入し、`includes` で \"JavaScript\" が含まれていなければ `push` で追加し、`join(\", \")` でカンマ区切りの1行にして `console.log` で表示してください。",
    "starterCode": "const skills = [\"HTML\", \"CSS\"];\n// ここにコードを書いてください\n",
    "answer": "const skills = [\"HTML\", \"CSS\"];\nif (!skills.includes(\"JavaScript\")) {\n  skills.push(\"JavaScript\");\n}\nconsole.log(skills.join(\", \"));",
    "explanation": "includes で存在確認し、なければ push で追加、join で表示用の文字列にまとめる流れです。タグやスキル一覧を動的に更新・表示する場面で使えるパターンです。",
    "learningPoints": [
      "includes と push を組み合わせて重複なく追加できる",
      "join で配列を表示用の文字列に変換できる",
      "配列メソッドを連携させて実用的な処理が書ける"
    ],
    "hints": [
      "if (!skills.includes(\"JavaScript\")) { ... } で含まれていないときだけ処理します",
      "skills.push(\"JavaScript\"); で要素を追加します",
      "console.log(skills.join(\", \")); でカンマ区切りの文字列を表示します"
    ],
    "testCases": [
      { "input": [], "expected": "HTML, CSS, JavaScript" }
    ]
  }
]
